Metadata-Version: 1.1
Name: rumps
Version: 0.2.2
Summary: Ridiculously Uncomplicated Mac os x Python Statusbar apps.
Home-page: https://github.com/jaredks/rumps
Author: Jared Suttles
Author-email: UNKNOWN
License: BSD License
Platform: UNKNOWN
Classifier: Development Status :: 4 - Beta
Classifier: Environment :: MacOS X
Classifier: Environment :: MacOS X :: Cocoa
Classifier: Intended Audience :: Developers
Classifier: License :: OSI Approved :: BSD License
Classifier: Operating System :: MacOS :: MacOS X
Classifier: Programming Language :: Python
Classifier: Programming Language :: Objective C
Classifier: Topic :: Software Development :: Libraries :: Python Modules
